[
	{
    "id": 1,
		"title": "Nyckeln till frihet",
		"year": "1994",
		"genres": [
			"Crime",
			"Drama"
		],
		"ratings": [8, 8, 6, 10, 2, 3, 4, 5, 4, 9, 3, 9, 6, 10, 4, 8, 10, 1, 2, 8, 1, 9, 5, 4, 4, 2, 4, 6, 9, 10],
		"duration": "PT142M",
		"releaseDate": "1995-03-03",
		"originalTitle": "The Shawshank Redemption",
		"storyline": "Chronicles the experiences of a formerly successful banker as a prisoner in the gloomy jailhouse of Shawshank after being found guilty of a crime he did not commit. The film portrays the man's unique way of dealing with his new, torturous life; along the way he befriends a number of fellow prisoners, most notably a wise long-term inmate named Red.                Written by\nJ-S-Golden",
		"actors": [
			"Tim Robbins",
			"Morgan Freeman",
			"Bob Gunton"
		],
		"posterurl": "https://images-na.ssl-images-amazon.com/images/M/MV5BODU4MjU4NjIwNl5BMl5BanBnXkFtZTgwMDU2MjEyMDE@._V1_SY500_CR0,0,336,500_AL_.jpg"
	},
	{
    "id": 2,
		"title": "Gudfadern",
		"year": "1972",
		"genres": [
			"Crime",
			"Drama"
		],
		"ratings": [6, 10, 4, 10, 1, 3, 7, 2, 3, 3, 3, 4, 2, 5, 6, 9, 10, 8, 7, 4, 8, 9, 9, 10, 4, 6, 2, 9, 7, 7],
		"duration": "PT175M",
		"releaseDate": "1972-09-27",
		"originalTitle": "The Godfather",
		"storyline": "When the aging head of a famous crime family decides to transfer his position to one of his subalterns, a series of unfortunate events start happening to the family, and a war begins between all the well-known families leading to insolence, deportation, murder and revenge, and ends with the favorable successor being finally chosen.                Written by\nJ. S. Golden",
		"actors": [
			"Marlon Brando",
			"Al Pacino",
			"James Caan"
		],
		"posterurl": "https://images-na.ssl-images-amazon.com/images/M/MV5BZTRmNjQ1ZDYtNDgzMy00OGE0LWE4N2YtNTkzNWQ5ZDhlNGJmL2ltYWdlL2ltYWdlXkEyXkFqcGdeQXVyNjU0OTQ0OTY@._V1_SY500_CR0,0,352,500_AL_.jpg"
	},
	{
    "id": 3,
		"title": "Gudfadern del II",
		"year": "1974",
		"genres": [
			"Crime",
			"Drama"
		],
		"ratings": [2, 5, 1, 1, 8, 4, 2, 3, 10, 10, 4, 9, 8, 9, 7, 6, 6, 9, 9, 4, 1, 8, 4, 5, 7, 7, 7, 1, 10, 6],
		"duration": "PT202M",
		"releaseDate": "1975-07-28",
		"originalTitle": "The Godfather: Part II",
		"storyline": "The continuing saga of the Corleone crime family tells the story of a young Vito Corleone growing up in Sicily and in 1910s New York; and follows Michael Corleone in the 1950s as he attempts to expand the family business into Las Vegas, Hollywood and Cuba.                Written by\nKeith Loh <loh@sfu.ca>",
		"actors": [
			"Al Pacino",
			"Robert De Niro",
			"Robert Duvall"
		],
		"posterurl": "https://images-na.ssl-images-amazon.com/images/M/MV5BMjZiNzIxNTQtNDc5Zi00YWY1LThkMTctMDgzYjY4YjI1YmQyL2ltYWdlL2ltYWdlXkEyXkFqcGdeQXVyNjU0OTQ0OTY@._V1_SY500_CR0,0,351,500_AL_.jpg"
	},
	{
    "id": 4,
		"title": "The Dark Knight",
		"year": "2008",
		"genres": [
			"Action",
			"Crime",
			"Drama"
		],
		"ratings": [3, 6, 4, 1, 6, 10, 6, 3, 5, 9, 1, 3, 1, 7, 8, 10, 6, 2, 8, 6, 7, 1, 4, 3, 8, 3, 10, 8, 10, 4],
		"duration": "PT152M",
		"releaseDate": "2008-07-25",
		"originalTitle": "",
		"storyline": "Set within a year after the events of Batman Begins, Batman, Lieutenant James Gordon, and new district attorney Harvey Dent successfully begin to round up the criminals that plague Gotham City until a mysterious and sadistic criminal mastermind known only as the Joker appears in Gotham, creating a new wave of chaos. Batman's struggle against the Joker becomes deeply personal, forcing him to \"confront everything he believes\" and improve his technology to stop him. A love triangle develops between Bruce Wayne, Dent and Rachel Dawes.                Written by\nLeon Lombardi",
		"actors": [
			"Christian Bale",
			"Heath Ledger",
			"Aaron Eckhart"
		],
		"posterurl": "https://images-na.ssl-images-amazon.com/images/M/MV5BMTMxNTMwODM0NF5BMl5BanBnXkFtZTcwODAyMTk2Mw@@._V1_SY500_CR0,0,337,500_AL_.jpg"
	},
	{
    "id": 5,
		"title": "12 edsvurna m\u00e4n",
		"year": "1957",
		"genres": [
			"Crime",
			"Drama"
		],
		"ratings": [3, 5, 3, 3, 10, 3, 4, 1, 6, 10, 2, 8, 4, 6, 8, 6, 1, 10, 4, 5, 9, 3, 2, 4, 8, 10, 10, 7, 9, 6],
		"duration": "PT96M",
		"releaseDate": "1957-07-29",
		"originalTitle": "12 Angry Men",
		"storyline": "The defense and the prosecution have rested and the jury is filing into the jury room to decide if a young man is guilty or innocent of murdering his father. What begins as an open-and-shut case of murder soon becomes a detective story that presents a succession of clues creating doubt, and a mini-drama of each of the jurors' prejudices and preconceptions about the trial, the accused, and each other. Based on the play, all of the action takes place on the stage of the jury room.                Written by\npjk <PETESID@VNET.IBM.COM>",
		"actors": [
			"Henry Fonda",
			"Lee J. Cobb",
			"Martin Balsam"
		],
		"posterurl": "https://images-na.ssl-images-amazon.com/images/M/MV5BODQwOTc5MDM2N15BMl5BanBnXkFtZTcwODQxNTEzNA@@._V1_SY500_CR0,0,333,500_AL_.jpg"
	},
	{
    "id": 6,
		"title": "Schindler's List",
		"year": "1993",
		"genres": [
			"Biography",
			"Drama",
			"History"
		],
		"ratings": [2, 6, 7, 8, 8, 6, 2, 4, 6, 2, 3, 3, 5, 9, 5, 10, 9, 5, 5, 2, 10, 4, 8, 7, 4, 10, 2, 10, 4, 10],
		"duration": "PT195M",
		"releaseDate": "1994-03-04",
		"originalTitle": "",
		"storyline": "Oskar Schindler is a vainglorious and greedy German businessman who becomes an unlikely humanitarian amid the barbaric German Nazi reign when he feels compelled to turn his factory into a refuge for Jews. Based on the true story of Oskar Schindler who managed to save about 1100 Jews from being gassed at the Auschwitz concentration camp, it is a testament to the good in all of us.                Written by\nHarald Mayr <marvin@bike.augusta.de>",
		"actors": [
			"Liam Neeson",
			"Ralph Fiennes",
			"Ben Kingsley"
		],
		"posterurl": "https://images-na.ssl-images-amazon.com/images/M/MV5BNDE4OTMxMTctNmRhYy00NWE2LTg3YzItYTk3M2UwOTU5Njg4XkEyXkFqcGdeQXVyNjU0OTQ0OTY@._V1_SY500_CR0,0,333,500_AL_.jpg"
	},
	{
    "id": 7,
		"title": "Pulp Fiction",
		"year": "1994",
		"genres": [
			"Crime",
			"Drama"
		],
		"ratings": [2, 9, 7, 7, 7, 2, 2, 4, 1, 9, 6, 3, 4, 10, 8, 6, 7, 5, 9, 4, 3, 5, 9, 3, 8, 2, 6, 7, 4, 4],
		"duration": "PT154M",
		"releaseDate": "1994-11-25",
		"originalTitle": "",
		"storyline": "Jules Winnfield (Samuel L. Jackson) and Vincent Vega (John Travolta) are two hit men who are out to retrieve a suitcase stolen from their employer, mob boss Marsellus Wallace (Ving Rhames). Wallace has also asked Vincent to take his wife Mia (Uma Thurman) out a few days later when Wallace himself will be out of town. Butch Coolidge (Bruce Willis) is an aging boxer who is paid by Wallace to lose his weight. The lives of these seemingly unrelated people are woven together comprising of a series of funny, bizarre and uncalled-for incidents.                Written by\nSoumitra",
		"actors": [
			"John Travolta",
			"Uma Thurman",
			"Samuel L. Jackson"
		],
		"posterurl": "https://images-na.ssl-images-amazon.com/images/M/MV5BMTkxMTA5OTAzMl5BMl5BanBnXkFtZTgwNjA5MDc3NjE@._V1_SY500_CR0,0,336,500_AL_.jpg"
	},
	{
    "id": 8,
		"title": "Sagan om konungens \u00e5terkomst",
		"year": "2003",
		"genres": [
			"Adventure",
			"Drama",
			"Fantasy"
		],
		"ratings": [6, 3, 2, 7, 5, 2, 10, 10, 4, 5, 7, 1, 8, 4, 8, 7, 2, 8, 5, 5, 6, 3, 3, 10, 10, 2, 1, 8, 3, 5],
		"duration": "PT201M",
		"releaseDate": "2003-12-17",
		"originalTitle": "The Lord of the Rings: The Return of the King",
		"storyline": "The final confrontation between the forces of good and evil fighting for control of the future of Middle-earth. Hobbits Frodo and Sam reach Mordor in their quest to destroy the \"one ring\", while Aragorn leads the forces of good against Sauron's evil army at the stone city of Minas Tirith.                Written by\nJwelch5742",
		"actors": [
			"Elijah Wood",
			"Viggo Mortensen",
			"Ian McKellen"
		],
		"posterurl": "https://images-na.ssl-images-amazon.com/images/M/MV5BYWY1ZWQ5YjMtMDE0MS00NWIzLWE1M2YtODYzYTk2OTNlYWZmXkEyXkFqcGdeQXVyNDUyOTg3Njg@._V1_SY500_SX334_AL_.jpg"
	}
]